drf_yasg_json_api/__init__.py
drf_yasg_json_api/deprecation.py
drf_yasg_json_api/utils.py
drf_yasg_json_api/view_inspectors.py
drf_yasg_json_api/inspectors/__init__.py
drf_yasg_json_api/inspectors/field.py
drf_yasg_json_api/inspectors/query.py
drf_yasg_json_api/inspectors/view.py
drf_yasg_json_api-0.9.1.dist-info/LICENSE.rst
drf_yasg_json_api-0.9.1.dist-info/METADATA
drf_yasg_json_api-0.9.1.dist-info/WHEEL
drf_yasg_json_api-0.9.1.dist-info/top_level.txt
drf_yasg_json_api-0.9.1.dist-info/RECORD
